README.txt
setup.cfg
setup.py
tests/base.py
tests/databasesetup.py
tests/model.py
tests/test_controller_security.py
tests/test_middleware.py
tests/session/container_file/0/05/05be853f36b7aed2728c760ce100527b.cache
tests/session/container_file/1/1b/1bbcb751fc18a59eaa0f6ff37969d841.cache
tests/session/container_file/3/32/3207d0cdd2981f1701a4b0d579795a91.cache
tests/session/container_file/4/48/4899dd6850d0c63f0fa2012b4123cc1f.cache
tests/session/container_file/6/65/65c78475353b8a6274ae5633b9a73fcc.cache
tests/session/container_file/7/73/7374b0cf54d1abad47777c46b006c2b2.cache
tests/session/container_file/7/7a/7a4a37d60ac6fa5d6249f1e9739b324a.cache
tests/session/container_file/8/87/87a69fd9555b274eb4d7e99964a63574.cache
tests/session/container_file/a/a9/a934cb70c7b3637eeb80a3f174d43033.cache
tests/session/container_file/b/b2/b25262ba7df59a577fed2309827dded4.cache
tests/session/container_file/c/c0/c03125645060762c577e3ce66151e419.cache
tests/session/container_file/d/df/df07c93c16890d8abb89d1bb5aa8fb7e.cache
tests/session/container_file/d/df/dfe0b67a73c3b7bde954b0fe31d8002e.cache
tests/session/container_file/e/eb/eba646a2105fe66d6a10587497351fbc.cache
tg/__init__.py
tg.ext.repoze.who.egg-info/PKG-INFO
tg.ext.repoze.who.egg-info/SOURCES.txt
tg.ext.repoze.who.egg-info/dependency_links.txt
tg.ext.repoze.who.egg-info/entry_points.txt
tg.ext.repoze.who.egg-info/namespace_packages.txt
tg.ext.repoze.who.egg-info/not-zip-safe
tg.ext.repoze.who.egg-info/requires.txt
tg.ext.repoze.who.egg-info/top_level.txt
tg/ext/__init__.py
tg/ext/repoze/__init__.py
tg/ext/repoze/who/__init__.py
tg/ext/repoze/who/authorize.py
tg/ext/repoze/who/middleware.py