Metadata-Version: 1.0
Name: tg.ext.repoze.who
Version: 0.1-r26
Summary: tg.ext.repoze.who are repoze.who plugins for TurboGears 2
Home-page: http://www.repoze.org
Author: Chris McDonough, Florent Aide, Christopher Perkins
Author-email: repoze-dev@lists.repoze.org
License: BSD-derived (http://www.repoze.org/LICENSE.txt)
Keywords: web application server wsgi tg2
Platform: UNKNOWN
Classifier: Development Status :: 1 - Planning
Classifier: Intended Audience :: Developers
Classifier: Programming Language :: Python
Classifier: Topic :: Internet :: WWW/HTTP
Classifier: Topic :: Internet :: WWW/HTTP :: Dynamic Content
Classifier: Topic :: Internet :: WWW/HTTP :: WSGI
Classifier: Topic :: Internet :: WWW/HTTP :: WSGI :: Application
